Metadata-Version: 1.0
Name: w600tool
Version: 0.1.0
Summary: A Firmware upload tool for Winner Micro W600 & W601 WiFim
Home-page: https://github.com/wemos/w600tool
Author: wemos
Author-email: support@wemos.cc
License: UNKNOWN
Keywords: w600,w600tool
Platform: any
